lytiva/__init__.py
lytiva/protocol.py
lytiva_connect-1.0.1.dist-info/METADATA
lytiva_connect-1.0.1.dist-info/WHEEL
lytiva_connect-1.0.1.dist-info/top_level.txt
lytiva_connect-1.0.1.dist-info/RECORD
