Metadata-Version: 2.4
Name: lytiva-connect
Version: 1.0.1
Summary: A Python library for interacting with Lytiva devices via MQTT.
Author-email: Lytiva <iot@lytiva.com>
Project-URL: Homepage, https://github.com/lytiva/lytiva-connect
Project-URL: Bug Tracker, https://github.com/lytiva/lytiva-connect/issues
Classifier: Programming Language :: Python :: 3
Classifier: License :: OSI Approved :: MIT License
Classifier: Operating System :: OS Independent
Requires-Python: >=3.10
